decree_tree/__init__.py
decree_tree/_version.py
decree_tree/assembled.py
decree_tree/base.py
decree_tree/decree.py
decree_tree/extras.py
decree_tree/parser.py
decree_tree/py.typed
decree_tree/tree.py
decree_tree-0.3.0.dist-info/LICENSE.txt
decree_tree-0.3.0.dist-info/METADATA
decree_tree-0.3.0.dist-info/WHEEL
decree_tree-0.3.0.dist-info/RECORD
