Metadata-Version: 2.3
Name: decree-tree
Version: 0.3.0
Summary: A minimal way to create nested argparse-based subcommands in scripts.
License: Apache-2.0
Keywords: command,cli
Author: Jared Ahern
Author-email: jared.ahern.dev@gmail.com
Maintainer: Jared Ahern
Maintainer-email: jared.ahern.dev@gmail.com
Requires-Python: >=3.10
Classifier: Development Status :: 4 - Beta
Classifier: Environment :: Console
Classifier: Intended Audience :: Developers
Classifier: License :: OSI Approved :: Apache Software License
Classifier: Natural Language :: English
Classifier: Operating System :: OS Independent
Classifier: Programming Language :: Python :: 3
Classifier: Topic :: Software Development :: Libraries :: Python Modules
Classifier: Topic :: System :: Shells
Classifier: Typing :: Typed
Requires-Dist: typing-extensions (>=4.6.0)
Project-URL: Documentation, https://elasmocalc.net/decree-tree
Project-URL: Homepage, https://gitlab.com/elasmocalc/decree-tree
Project-URL: Repository, https://gitlab.com/elasmocalc/decree-tree
Project-URL: issues, https://gitlab.com/elasmocalc/decree-tree/issues
Project-URL: pypi, https://pypi.org/project/decree-tree/
